poussetaches.py
poussetaches-0.2.0.dist-info/LICENSE
poussetaches-0.2.0.dist-info/METADATA
poussetaches-0.2.0.dist-info/WHEEL
poussetaches-0.2.0.dist-info/top_level.txt
poussetaches-0.2.0.dist-info/RECORD
